CHANGES.txt
LICENSE.txt
MANIFEST.in
README.txt
cliargs.py
setup.py
CLIArgs.egg-info/PKG-INFO
CLIArgs.egg-info/SOURCES.txt
CLIArgs.egg-info/dependency_links.txt
CLIArgs.egg-info/top_level.txt
examples/test.py