Metadata-Version: 1.0
Name: CLIArgs
Version: 1.0
Summary: Absolutely trivial command line arguments
Home-page: http://pypi.python.org/pypi/CLIArgs/
Author: Pavel Panchekha
Author-email: pavpanchekha@gmail.com
License: LICENSE.txt
Platform: UNKNOWN
Classifier: Development Status :: 4 - Beta
Classifier: Intended Audience :: Developers
Classifier: License :: OSI Approved :: GNU General Public License (GPL)
Classifier: Programming Language :: Python :: 2.6
Classifier: Topic :: Software Development :: Libraries :: Python Modules
